ytservice/__init__.py
ytservice/common.py
ytservice/daemon.py
ytservice/exception_handlers.py
ytservice/model.py
ytservice/service.py
ytservice/version.py
ytservice/ytclient.py
yt_service-0.0.10.dist-info/METADATA
yt_service-0.0.10.dist-info/WHEEL
yt_service-0.0.10.dist-info/entry_points.txt
yt_service-0.0.10.dist-info/top_level.txt
yt_service-0.0.10.dist-info/RECORD
